pinkmess/__init__.py
pinkmess/__main__.py
pinkmess/collection.py
pinkmess/config.py
pinkmess/note.py
pinkmess/py.typed
pinkmess/agents/__init__.py
pinkmess/agents/common.py
pinkmess/agents/note_summarization.py
pinkmess/agents/note_tag_suggestion.py
pinkmess/cli/__init__.py
pinkmess/cli/collection.py
pinkmess/cli/config.py
pinkmess/cli/main.py
pinkmess/cli/note.py
pinkmess-0.2.0.dist-info/METADATA
pinkmess-0.2.0.dist-info/WHEEL
pinkmess-0.2.0.dist-info/entry_points.txt
pinkmess-0.2.0.dist-info/licenses/LICENSE.md
pinkmess-0.2.0.dist-info/RECORD
