Metadata-Version: 2.4
Name: pinkmess
Version: 0.2.0
Summary: A simple PKMS manager for lazy people.
Author-email: leodiegues <leodiegues@pm.me>
License-File: LICENSE.md
Requires-Python: <4.0,>=3.10
Requires-Dist: platformdirs>=4.3.6
Requires-Dist: pydantic-ai>=0.0.21
Requires-Dist: pydantic-settings[toml]>=2.7.1
Requires-Dist: python-frontmatter>=1.1.0
Requires-Dist: rtoml>=0.12.0
